ftests/__init__.py
ftests/__main__.py
ftests/args_type_checkers.py
ftests/cli_args.py
ftests/expectation_result.py
ftests/test_result.py
ftests/tests_definition.py
ftests/expectations/__init__.py
ftests/expectations/_base_expectation.py
ftests/expectations/_completed_process_expectation.py
ftests/expectations/_return_code_expectation.py
ftests/expectations/_stderr_expectation.py
ftests/expectations/_stdout_expectation.py
ftests/test_cases/__init__.py
ftests/test_cases/_command_test_case.py
ftests/test_cases/_test_case.py
tests/__init__.py
tests/helpers.py
tests/test_cli_args.py
tests/test_expectation_result.py
tests/test_tests_definition.py
tests/test_cases/__init__.py
tests/test_cases/test_command_test_case.py
tests/test_cases/test_test_case.py
tests/test_expectations/__init__.py
tests/test_expectations/test_completed_process_expectation.py
tests/test_expectations/test_return_code_expectation.py
tests/test_expectations/test_stderr_expectation.py
tests/test_expectations/test_stdout_expectation.py
ftests-0.0.3.dist-info/LICENSE
ftests-0.0.3.dist-info/METADATA
ftests-0.0.3.dist-info/WHEEL
ftests-0.0.3.dist-info/entry_points.txt
ftests-0.0.3.dist-info/top_level.txt
ftests-0.0.3.dist-info/RECORD
